{
  "data": {
    "domain": "mifarmhousepizza.com",
    "restaurantName": "Michigan Farmhouse Pizza",
    "placeId": "ChIJE2jOcr1rGIgR1F-N2hZC5aQ",
    "overallScore": 86,
    "performance": 100,
    "seo": 68,
    "mobile": 66,
    "userExperience": 92,
    "issues": [
      {
        "type": "seo",
        "severity": "critical",
        "title": "🎯 Missing in Action: Zero SEO Strategy",
        "description": "Your restaurant is invisible to potential customers searching online. No keyword optimization detected.",
        "impact": "high",
        "effort": "medium",
        "icon": "🔍",
        "color": "orange",
        "urgency": "high",
        "businessImpact": "Missing out on 70% of customers who search online before visiting"
      },
      {
        "type": "mobile",
        "severity": "critical",
        "title": "📱 Mobile Disaster: Customers Can't Order",
        "description": "Mobile performance data unavailable - API configuration required",
        "impact": "high",
        "effort": "medium",
        "icon": "📱",
        "color": "red",
        "urgency": "immediate",
        "businessImpact": "60% of restaurant orders come from mobile - this is costing you sales"
      }
    ],
    "recommendations": [
      {
        "title": "Improve website performance",
        "description": "Improve website performance",
        "impact": "medium",
        "effort": "medium",
        "category": "technical"
      },
      {
        "title": "Enhance social media presence",
        "description": "Enhance social media presence",
        "impact": "medium",
        "effort": "medium",
        "category": "marketing"
      }
    ],
    "keywords": [],
    "competitiveOpportunityKeywords": [
      {
        "keyword": "pizza near me",
        "position": 0,
        "searchVolume": 30,
        "difficulty": 0,
        "intent": "local",
        "cpc": 0,
        "competition": 0,
        "opportunity": 75,
        "url": null,
        "title": null,
        "description": null,
        "isNew": null,
        "isLost": null,
        "positionChange": null,
        "previousPosition": null
      },
      {
        "keyword": "pizza delivery Clarksville",
        "position": 1,
        "searchVolume": 0,
        "difficulty": 0,
        "intent": "transactional",
        "cpc": 0,
        "competition": 0,
        "opportunity": 75,
        "url": "https://mifarmhousepizza.com/",
        "title": "MI FARMHOUSE PIZZA",
        "description": null,
        "isNew": null,
        "isLost": null,
        "positionChange": null,
        "previousPosition": null
      },
      {
        "keyword": "best pizza Clarksville",
        "position": 1,
        "searchVolume": 0,
        "difficulty": 0,
        "intent": "commercial",
        "cpc": 0,
        "competition": 0,
        "opportunity": 75,
        "url": "https://mifarmhousepizza.com/",
        "title": "MI FARMHOUSE PIZZA",
        "description": null,
        "isNew": null,
        "isLost": null,
        "positionChange": null,
        "previousPosition": null
      },
      {
        "keyword": "pizza",
        "position": 0,
        "searchVolume": 30,
        "difficulty": 0,
        "intent": "navigational",
        "cpc": 0,
        "competition": 0,
        "opportunity": 75,
        "url": null,
        "title": null,
        "description": null,
        "isNew": null,
        "isLost": null,
        "positionChange": null,
        "previousPosition": null
      },
      {
        "keyword": "pizza places near me",
        "position": 0,
        "searchVolume": 10,
        "difficulty": 0,
        "intent": "local",
        "cpc": 0,
        "competition": 0,
        "opportunity": 75,
        "url": null,
        "title": null,
        "description": null,
        "isNew": null,
        "isLost": null,
        "positionChange": null,
        "previousPosition": null
      },
      {
        "keyword": "pizza Clarksville Michigan",
        "position": 1,
        "searchVolume": 0,
        "difficulty": 0,
        "intent": "navigational",
        "cpc": 0,
        "competition": 0,
        "opportunity": 75,
        "url": "https://mifarmhousepizza.com/",
        "title": "MI FARMHOUSE PIZZA",
        "description": null,
        "isNew": null,
        "isLost": null,
        "positionChange": null,
        "previousPosition": null
      },
      {
        "keyword": "pizza delivery near me",
        "position": 0,
        "searchVolume": 10,
        "difficulty": 0,
        "intent": "transactional",
        "cpc": 0,
        "competition": 0,
        "opportunity": 75,
        "url": null,
        "title": null,
        "description": null,
        "isNew": null,
        "isLost": null,
        "positionChange": null,
        "previousPosition": null
      },
      {
        "keyword": "pizza open now",
        "position": 0,
        "searchVolume": 0,
        "difficulty": 0,
        "intent": "navigational",
        "cpc": 0,
        "competition": 0,
        "opportunity": 75,
        "url": null,
        "title": null,
        "description": null,
        "isNew": null,
        "isLost": null,
        "positionChange": null,
        "previousPosition": null
      }
    ],
    "enhancedKeywordDiscovery": [],
    "competitiveGaps": [],
    "keywordAnalysis": {
      "targetKeywords": [],
      "rankingPositions": [],
      "searchVolumes": {},
      "opportunities": [
        "Competitors rank higher for delivery keywords",
        "Missing from \"best restaurant\" searches"
      ]
    },
    "domainRankedKeywords": [],
    "localCompetitorData": [],
    "localPackReport": {
      "summary": {
        "visibility_score": 75,
        "keywords_appeared": 6,
        "total_keywords": 8,
        "average_position": 1,
        "best_position": 1
      },
      "keyword_results": [
        {
          "keyword": "pizza near me",
          "found": true,
          "position": 1,
          "confidence": 100,
          "matched_fields": [
            "title",
            "url"
          ],
          "local_pack_data": {
            "name": "Michigan Farmhouse Pizza",
            "address": "Clarksville, MI ",
            "website": "https://mifarmhousepizza.com/?y_source=1_NDYxNjAxNDAtNzE1LWxvY2F0aW9uLndlYnNpdGU%3D",
            "phone": "(616) 504-5040",
            "rating": 4.6,
            "reviews": 454
          },
          "competitors": []
        },
        {
          "keyword": "pizza",
          "found": true,
          "position": 1,
          "confidence": 100,
          "matched_fields": [
            "title",
            "url"
          ],
          "local_pack_data": {
            "name": "Michigan Farmhouse Pizza",
            "address": "Clarksville, MI ",
            "website": "https://mifarmhousepizza.com/?y_source=1_NDYxNjAxNDAtNzE1LWxvY2F0aW9uLndlYnNpdGU%3D",
            "phone": "(616) 504-5040",
            "rating": 4.6,
            "reviews": 454
          },
          "competitors": []
        },
        {
          "keyword": "best pizza Clarksville",
          "found": true,
          "position": 1,
          "confidence": 100,
          "matched_fields": [
            "title",
            "url"
          ],
          "local_pack_data": {
            "name": "Michigan Farmhouse Pizza",
            "address": "Clarksville, MI ",
            "website": "https://mifarmhousepizza.com/?y_source=1_NDYxNjAxNDAtNzE1LWxvY2F0aW9uLndlYnNpdGU%3D",
            "phone": "(616) 504-5040",
            "rating": 4.6,
            "reviews": 454
          },
          "competitors": []
        },
        {
          "keyword": "pizza delivery near me",
          "found": true,
          "position": 1,
          "confidence": 100,
          "matched_fields": [
            "title",
            "url"
          ],
          "local_pack_data": {
            "name": "Michigan Farmhouse Pizza",
            "address": "Clarksville, MI ",
            "website": "https://mifarmhousepizza.com/?y_source=1_NDYxNjAxNDAtNzE1LWxvY2F0aW9uLndlYnNpdGU%3D",
            "phone": "(616) 504-5040",
            "rating": 4.6,
            "reviews": 454
          },
          "competitors": []
        },
        {
          "keyword": "pizza Clarksville Michigan",
          "found": true,
          "position": 1,
          "confidence": 100,
          "matched_fields": [
            "title",
            "url"
          ],
          "local_pack_data": {
            "name": "Michigan Farmhouse Pizza",
            "address": "Clarksville, MI ",
            "website": "https://mifarmhousepizza.com/?y_source=1_NDYxNjAxNDAtNzE1LWxvY2F0aW9uLndlYnNpdGU%3D",
            "phone": "(616) 504-5040",
            "rating": 4.6,
            "reviews": 454
          },
          "competitors": []
        },
        {
          "keyword": "top pizza Clarksville",
          "found": false,
          "confidence": 0,
          "matched_fields": []
        },
        {
          "keyword": "pizza restaurant near me",
          "found": true,
          "position": 1,
          "confidence": 100,
          "matched_fields": [
            "title",
            "url"
          ],
          "local_pack_data": {
            "name": "Michigan Farmhouse Pizza",
            "address": "Clarksville, MI ",
            "website": "https://mifarmhousepizza.com/?y_source=1_NDYxNjAxNDAtNzE1LWxvY2F0aW9uLndlYnNpdGU%3D",
            "phone": "(616) 504-5040",
            "rating": 4.6,
            "reviews": 454
          },
          "competitors": []
        },
        {
          "keyword": "pizza food Clarksville",
          "found": false,
          "confidence": 0,
          "matched_fields": []
        }
      ],
      "recommendations": [
        "Not appearing for \"top pizza Clarksville\", \"pizza food Clarksville\" - optimize Google My Business profile with these keywords"
      ],
      "scan_metadata": {
        "location": "Clarksville,Michigan,United States",
        "timestamp": "2025-09-15T16:50:02.819Z",
        "total_scan_time_ms": 105017
      }
    },
    "competitors": [],
    "competitorIntelligence": {
      "organicCompetitors": [],
      "keywordGaps": [
        "best pizza delivery",
        "pizza restaurant online ordering"
      ],
      "trafficEstimates": []
    },
    "serpFeatures": [],
    "domainAuthority": 84,
    "screenshot": null,
    "seoAnalysis": {
      "title": "No title found",
      "metaDescription": "No meta description found",
      "h1Tags": [],
      "imageCount": 0,
      "internalLinks": 0,
      "externalLinks": 0,
      "schemaMarkup": false
    },
    "metrics": {
      "fcp": 0,
      "lcp": 0,
      "cls": 0,
      "fid": 0
    },
    "backlinks": 0,
    "organicTraffic": 0,
    "scanDate": "2025-09-15T16:50:12.169Z",
    "businessProfile": {
      "name": "Michigan Farmhouse Pizza",
      "address": "109 N Main St, Clarksville, MI 48815, USA",
      "rating": 4.6,
      "reviewCount": 454,
      "phoneNumber": "(616) 504-5040",
      "website": "https://mifarmhousepizza.com/?y_source=1_NDYxNjAxNDAtNzE1LWxvY2F0aW9uLndlYnNpdGU%3D",
      "formatted_address": "109 N Main St, Clarksville, MI 48815, USA",
      "address_components": [
        {
          "long_name": "109",
          "short_name": "109",
          "types": [
            "street_number"
          ]
        },
        {
          "long_name": "North Main Street",
          "short_name": "N Main St",
          "types": [
            "route"
          ]
        },
        {
          "long_name": "Clarksville",
          "short_name": "Clarksville",
          "types": [
            "locality",
            "political"
          ]
        },
        {
          "long_name": "Campbell Township",
          "short_name": "Campbell Township",
          "types": [
            "administrative_area_level_3",
            "political"
          ]
        },
        {
          "long_name": "Ionia County",
          "short_name": "Ionia County",
          "types": [
            "administrative_area_level_2",
            "political"
          ]
        },
        {
          "long_name": "Michigan",
          "short_name": "MI",
          "types": [
            "administrative_area_level_1",
            "political"
          ]
        },
        {
          "long_name": "United States",
          "short_name": "US",
          "types": [
            "country",
            "political"
          ]
        },
        {
          "long_name": "48815",
          "short_name": "48815",
          "types": [
            "postal_code"
          ]
        }
      ],
      "state": "Michigan",
      "city": "Clarksville",
      "place_id": "ChIJE2jOcr1rGIgR1F-N2hZC5aQ",
      "business_status": "OPERATIONAL",
      "types": [
        "establishment",
        "food",
        "point_of_interest",
        "restaurant"
      ],
      "reviews": [
        {
          "author_name": "Steven Morgan",
          "author_url": "https://www.google.com/maps/contrib/103920091266228441663/reviews",
          "language": "en",
          "original_language": "en",
          "profile_photo_url": "https://lh3.googleusercontent.com/a-/ALV-UjWbRhjV2FAv-vNqpb1h1b_7R-bTMi87hl8D--2ebAeyXCtJsI1Sbw=s128-c0x00000000-cc-rp-mo-ba4",
          "rating": 5,
          "relative_time_description": "a month ago",
          "text": "Outstanding pizza and wings.  Service was great, a perfect low key place gather with good food",
          "time": 1754840767,
          "translated": false
        },
        {
          "author_name": "Abby Bailey",
          "author_url": "https://www.google.com/maps/contrib/114114055856741483295/reviews",
          "language": "en",
          "original_language": "en",
          "profile_photo_url": "https://lh3.googleusercontent.com/a/ACg8ocLCXNDtXYYuGXFn3SrKPgtj6QkgGt_hs1vqvESSLcOy0xpiMw=s128-c0x00000000-cc-rp-mo",
          "rating": 5,
          "relative_time_description": "10 months ago",
          "text": "Michigan Farmhouse Pizza, Thank you for carrying my favorite drinks right now! I love that you support local breweries!  (Long Road) And better priced than Meijer. The Elk Sausage Pizza is the bomb! Keep up the great work!\n\nI have been ordering from Farmhouse for the last 3 years or better, and I have always enjoyed their Pizza, Subs and Wraps! Never had a bad experience, if something was wrong, I’d call and they would make it right. Great customer service.",
          "time": 1730595256,
          "translated": false
        },
        {
          "author_name": "Brian M.",
          "author_url": "https://www.google.com/maps/contrib/103807771352233437428/reviews",
          "language": "en",
          "original_language": "en",
          "profile_photo_url": "https://lh3.googleusercontent.com/a/ACg8ocKwF48P-sWZGrpl5hL5y2Lnfe6Y0odSHp38W4gHIbwE0Lm8Xw=s128-c0x00000000-cc-rp-mo",
          "rating": 5,
          "relative_time_description": "a month ago",
          "text": "Have gotten pizza a number of times and always good. They have some unique choices that change with time. Picked up a deluxe sub tonight and it was good. Nothing terribly wild or exceptional but a good solid sub. Friendly service.",
          "time": 1754434865,
          "translated": false
        },
        {
          "author_name": "Ali Nurmikko",
          "author_url": "https://www.google.com/maps/contrib/112975054850611002695/reviews",
          "language": "en",
          "original_language": "en",
          "profile_photo_url": "https://lh3.googleusercontent.com/a-/ALV-UjVWGpYFyHskD35yOrJPiGTOj9Hbzf7ZqmF1Crn-CmvKjv-q6OsN=s128-c0x00000000-cc-rp-mo",
          "rating": 5,
          "relative_time_description": "a month ago",
          "text": "We just moved to the area from GR and this has been a go-to for us! After being heavily spoiled with the food scene, we were worried about moving to a small town with less options. MI Farmhouse did not disappoint!!! Delicious pizza! Great specialty pizza flavors. We have only done carry out, but its been great!",
          "time": 1754064692,
          "translated": false
        },
        {
          "author_name": "Russell F",
          "author_url": "https://www.google.com/maps/contrib/109233339174768710301/reviews",
          "language": "en",
          "original_language": "en",
          "profile_photo_url": "https://lh3.googleusercontent.com/a/ACg8ocLpPx4vpG935fEig-GNj0t2vanOXyM8N-uzN0GQsmmtBRKR1A4=s128-c0x00000000-cc-rp-mo-ba4",
          "rating": 5,
          "relative_time_description": "3 months ago",
          "text": "I am in love with this Crab Rangoon Pizza.   It is a must try.\n\nMust update!  6/25. I just had their gluten free pizza crust.  Wow!  It tastes just like a regular flour crust.",
          "time": 1749422597,
          "translated": false
        }
      ],
      "photos": [
        {
          "height": 4000,
          "html_attributions": [
            "<a href=\"https://maps.google.com/maps/contrib/112271626265139837726\">Marc</a>"
          ],
          "photo_reference": "AciIO2eiLwufDHk9rHF29XEldT0Jwi3-3xsSifAoGSCJ7qpXxY2fdFD0WksZvn24YuEKh1u1RngKdp8S8YiDP25EYD1XQVucGeVzuyNWtN2l71zcB7dZj1GuO7GaYIennaV8fsWj4gcQLwFHhNiwI9PDlglO2XzFad9NlyIK9X4lpAJsOxqCaC857FaWiZZnnI2QOkCCcESOi8xpW7vYjb8rV9wGaxpvyQBmcnZ3Sq4SyuoazfmyyzQvHihynN_4KQJ47elnAp7a7L_ZrBhQeFuP8hdz30SkfeyxbU3X0D9KA1uPNDUu12nvEAj4E345H_9cGcIVmMEpwYtfeSyLwpY0I-V1swMHlTz5ufvOq1EZq6Im-loSpmojt2ZXyyoDrf364gcuRmD3ggGiRMzP0FCBPlnV-yf5nKXH1jeGTlszEWJRljQ",
          "width": 3000
        },
        {
          "height": 960,
          "html_attributions": [
            "<a href=\"https://maps.google.com/maps/contrib/103846558017331454466\">Michigan Farmhouse Pizza</a>"
          ],
          "photo_reference": "AciIO2d27VtlVep1eiujkl1Geqp-6Wdb3GBFEjAAFCeReLEs-9sOFtcMcXIqo8pWju-edMbPf2dUFv0-HGzQ3OQtpteXptJIU5WXfwWgx2_sKyJqGeqf2xjdRGLG_DobeGorKJAZzlnUsArQEn8gc-casd0dcGkqaSGk8gDGvm-J2YDx5GVWhE0IrxbPCW5N5NBaQBNoP0TcRwuPDM6skcAPfjaWxEE2yNI_ez6YMYAv0CfKYNX9O3fq9xsl4DF_I6K5Z6FK-BEqwTK9qnNtzzey37bEw0Fj8QQPSkbO_6ejIrmPjg",
          "width": 960
        },
        {
          "height": 1192,
          "html_attributions": [
            "<a href=\"https://maps.google.com/maps/contrib/103846558017331454466\">Michigan Farmhouse Pizza</a>"
          ],
          "photo_reference": "AciIO2eoOn6L6Uja6wG-EN7duoqZxVUYuwttiHOduUVV3aFK4CYbfFScaSub1Ld13q6kfh2tK67FQqierwHxU095R-Z2LOKD3XzGXRhZpXsVzvVmkIpPwwI2KzxfqhaIYZyYryiS4uaWzS0ewlF6DLU4QsrT84pdsEFkrPAo7j9JcIB7H2e9f5vxWyYTxERIk9WoVLhDp1F7Uh-I4LcHgJc7TuJfv9xloRo9sOkXQz9Xe34A6kaRxatU7o07K_lhN1ZG3bSAcAJlYO9ZECRCOPjTU1Y-925AP4oFKFxDHUtvR8QSfg",
          "width": 2119
        },
        {
          "height": 3000,
          "html_attributions": [
            "<a href=\"https://maps.google.com/maps/contrib/101881175393855044030\">Kellie Frees</a>"
          ],
          "photo_reference": "AciIO2c6c7kjrc-EbN1x6dLprd2W1gxuaggfNgG3O-41CUo1Ykp4yk7w6XsQ668vIiZBXb0FKzm5MqRmGpXXN_X9jRMH_tUO-3-vzvDfUuE3k_xhb-QUqUwkhvs-CVYhs2141AigB49ndPPA-ik4USqIQHeQHjNgF-_0b1PK9WwY6ekfpbGwY6IVWAbhin5S8McvNTcmZKz7oRMTeOVXQo0C42uwm6Xz-ZLb7zyoHN4YXAI8q6oE5fRjfsLn_Jn9ndq9dOrE9MquMVjZ-0no0Jfkh5NGsHq415iDvdElvfhfDWLlDWAXfZx3GwHctu1c99NQSfJ6zl5B3fG_g5OUQFBikIE7s901LEpzdkg08dJ2Y1cgkiuYkTGHLmJMUrgQNJW0l6qGZ36RMg7brTbdHR0ZrU1_LbRprMM-ZVgD4cTcgKb81Q",
          "width": 4000
        },
        {
          "height": 4000,
          "html_attributions": [
            "<a href=\"https://maps.google.com/maps/contrib/112271626265139837726\">Marc</a>"
          ],
          "photo_reference": "AciIO2fFlqXYisnYdDbNR-6O8-zDRkM8id8fSkkblRp06exwUh_S8hNLGOo1LIyK_Bvg-hA2bfg4IcOjyd9X8HuhfBXBPRtoRdr4joJhZMxf7-OqQ3bSUBMX_2QbWVbahDx0aezhDNOK6C_RzlmB9ct8iNqXbq_RQnKPdoSQ217HybJxvR30SSSzAUZEVBYBEt7qJrZ7zN-Z_8gD7mkXyLj_FidQPm1A4iEeZmacpZN9bqw7Jq7FXdA45pJgKXk7ZVNuszXtFCAvkkg1hEdleN7BsP6_-zqxpw49LM4FvoobBWox5SAVmsB92VJ_8ypwBU3rZklVMqxNscsIC5930Tw1XICyXKIlPW2IT0_FG_8ZB_YBoqnU2RjSKjN5hvtDllY7JKvJ_JbYBb0BjK6SDWO55Rltq_w2vhWs0hbmASwnqWM",
          "width": 3000
        },
        {
          "height": 3600,
          "html_attributions": [
            "<a href=\"https://maps.google.com/maps/contrib/113371796286625645821\">Lewis Butler</a>"
          ],
          "photo_reference": "AciIO2fvFuOydoEZ-eOUMMDzwPTjicCcN-oTpJNuxJnuHgYwnGsrPIsTan4tFMas6viwIXWAy7ES2Y6giq0NN25t5SnFFbBhV1CDpVfWC334DBjOWjhf4ZX3QHj_wyFpx0ed-q56d7cQ6Bmupps0X4nBlYv25IOxqM_7ozJpcbdx3MilCMhVmn2ShD7XAdHohXsEJa49PUDDcleAZMzotpYMm8uBDeh9lM7Y85vW0Ehlx2Ch-VUV5YS_DEeY_ufkKfBSQRgxmnaE0_9nxn-2CSXWqaQS7hOw1q1P9t7l3qtQD92dTzt1v4bDHcflD3wdKTOB7XKHDImYGtOBSuQyZCGgNYcDHwejik4yvs1-JRsDvqX5BWlGp7-MfHNnN1Pm_grh6740cdRoVWZmiM9RQ2uMhYfbBeBnS5QWjhuVHANubfH-5s6p",
          "width": 4800
        },
        {
          "height": 2448,
          "html_attributions": [
            "<a href=\"https://maps.google.com/maps/contrib/115556187879283315903\">Won Meow</a>"
          ],
          "photo_reference": "AciIO2eTHrBtrA8HjnkULDD_iMfWQIvH_sShDJMOzlQumrSt15JuTuJgArK6j5bl1P8Vtw-W952O1VQvgvinwxhsOpkxYF_hqdpIcTt5_09EI6rwb2y94V8uguhuSiwnX3OYMhTlbc7-HwZjjW4TZ2uFv5VEdYGCDO-MScB3PUCLWjdn6BSyM_dIqvN2hYgx7YhvNeum2mNYHFFIUGCiE1KeV1dZrhnlewwxIV1jzQRzqmfk_RWqJ9wji-DAfL5qONUsgeiYtUP1Hf37FmSwUN_TH2OBpohBCLOUrTqP-ryqUt1nAKeArubNj7kenmXEhKQgYg64ToZxg-1f3MHrGwL60naMe25sZk-LSSjlKgjaiX2AoDa3RsXX1-E-WmwwZhSflLss3bf0wZWUio6vWDYRFoJNzm4lvA0LtS0LXViArsdbwdA",
          "width": 3264
        },
        {
          "height": 562,
          "html_attributions": [
            "<a href=\"https://maps.google.com/maps/contrib/103846558017331454466\">Michigan Farmhouse Pizza</a>"
          ],
          "photo_reference": "AciIO2ftf63fFPV-kGiUmKR-_HWuOpturmNTfKXpVFUC74_4ItNM6i2g1TK6RyxLLtximkxRzixmOX5b27F5PhQwjNL5q27pFuKdQ7WP9X1hg_6LCNthfdKvz37xwB3deNXRmK6vGOQH3v7LbamWnOijYbm10GXD3YQ32rEeNA3oZJI7M1QqbEDFZlEVQEpQr4rRsrOyiMR95c03qfkMr3PfaxrAZOYY47NNOFy-e66ndThUQRiElJ5Xqm6qtzf5lKcBjXzosIR9sjv9TpDEYINSLLWrCsxBBrVDbWk-DA-EQ13ypQ",
          "width": 750
        },
        {
          "height": 960,
          "html_attributions": [
            "<a href=\"https://maps.google.com/maps/contrib/103846558017331454466\">Michigan Farmhouse Pizza</a>"
          ],
          "photo_reference": "AciIO2cftfirql8VHYVlT8Ty_3V0tlooq7kmYqSAFe2BgCKZYhpNIuRQyyj6u7itr7JY033jmwVR3J2M-MMaXHvI20KU0PsW-2tbmRPvl5Om_KJx8dAgnW0h2A-38msQOw3Wcp_D7bvQ-rnANQ9kJXOa87D8yA9M4rjwdnsYPcErrscMSJOuK-WWmAn8wa7c22lMP-LBsNgH2XnqZ-DVGF6EskzCZ6hLXnUHXd8c-P6bKvaPgXShQWACGFNY2fDclkbJw7k2pgxkD4d9kHR3XUraM3kzlKIfEYXM5Cyb5rBmxD3v4A",
          "width": 788
        },
        {
          "height": 4032,
          "html_attributions": [
            "<a href=\"https://maps.google.com/maps/contrib/103846558017331454466\">Michigan Farmhouse Pizza</a>"
          ],
          "photo_reference": "AciIO2dx3_rki2aElBO8QALOjXV-OFsxduOvslogKHqvLR9Dm66EJPkRWiICv-eg1fpUx7lpfHm-VTYKPMgBiwJC3m1eFmu0hpIh4kJi4Co90L2H6RqtumgSZTFnuSk_AyMOBw9Mbpf3nWrsQkb6qvWwVdQZXHLgA6awlVLORfjGzHq8HF2D9kbgL-CVjWs2hpt9zsoDx1beddRuk0vOhyd4yEG3A9DnkgdBTqfd27xT_CofFkrzJ-DrSLzZJcmESAC_daOTNpE0CmMl9OafsoOJNZmRtUXLJaTa87y1KJQcjiOmOw",
          "width": 3024
        }
      ],
      "photoCount": 10,
      "opening_hours": {
        "open_now": true,
        "periods": [
          {
            "close": {
              "day": 0,
              "time": "2100"
            },
            "open": {
              "day": 0,
              "time": "1500"
            }
          },
          {
            "close": {
              "day": 1,
              "time": "2100"
            },
            "open": {
              "day": 1,
              "time": "1100"
            }
          },
          {
            "close": {
              "day": 2,
              "time": "2100"
            },
            "open": {
              "day": 2,
              "time": "1100"
            }
          },
          {
            "close": {
              "day": 3,
              "time": "2100"
            },
            "open": {
              "day": 3,
              "time": "1100"
            }
          },
          {
            "close": {
              "day": 4,
              "time": "2100"
            },
            "open": {
              "day": 4,
              "time": "1100"
            }
          },
          {
            "close": {
              "day": 5,
              "time": "2100"
            },
            "open": {
              "day": 5,
              "time": "1100"
            }
          },
          {
            "close": {
              "day": 6,
              "time": "2200"
            },
            "open": {
              "day": 6,
              "time": "1100"
            }
          }
        ],
        "weekday_text": [
          "Monday: 11:00 AM – 9:00 PM",
          "Tuesday: 11:00 AM – 9:00 PM",
          "Wednesday: 11:00 AM – 9:00 PM",
          "Thursday: 11:00 AM – 9:00 PM",
          "Friday: 11:00 AM – 9:00 PM",
          "Saturday: 11:00 AM – 10:00 PM",
          "Sunday: 3:00 – 9:00 PM"
        ]
      },
      "price_level": 2,
      "editorial_summary": null,
      "url": "https://maps.google.com/?cid=11881975857810333652",
      "social_media": null
    },
    "businessPhotos": [
      "https://maps.googleapis.com/maps/api/place/photo?maxwidth=400&photo_reference=AciIO2elO33-c6JiqmJxzGasipsnr40BIdBpSVNRomPGAGPJhSsqwgrF84Ld8ewa3lk_UhslpF9SYxNNiXaGc32HWMC96Lu5zoyNiiLIYTk0j2WYC__JVu7e8PBrJdlHWfqUbhrxa9pl5t5zq_yVMwZ1DA4hp_8Qt7DXkY0AXtEJoVy3v-BZVG9yx1WMdY8VDbHRtO-EPJIXbM3f0b5kZqvgcLLOayPXH5dvOIFeOxq6oAhjXpofEnEDhMQWcMlB9noiof2QeGtobAV5jk1y7cMfAMjL1Mr0QyUn48qEFDHKmjtTRnA4fs774hWfreZH0Dh1c2Kra_KobJ0FZu-p9i7BjzATu2_FdZMkMB889fRIO_LaKlqNEJOft_03A_xWregaN0LfrBRQqTke1LaRNjjH__3pn1hmLCmhAHwt19toBlG789M&key=AIzaSyADLqCeJAQo6qES8aNsfGH2n8fRjOAAMrQ",
      "https://maps.googleapis.com/maps/api/place/photo?maxwidth=400&photo_reference=AciIO2ewhm47pJ0peRJ96VRPpNN1NvcxJgd6OWYlW7S2AVPMR2hKJC1KjHhmpxOS_JR5rs5aW4XN41B30u84C-nd1r1uTWh5rsY0p-JbLeOUxUXl8Mvy9wSxVwQ8mKJ8nzfCcaGosCFXj1Ifl__lE56VuILTLkKI7ay5jF3BRjSHHX8DR3NjCEzRjQA89KwebdTkMc4GXF90xzE6jr_f3vynKwnYmuSUCsw-ta7X7RT92e-0-1NlOMk5PYS01Cha0wdBdtELyi0IAodB6EQvlO06cEu6WawMlXuGA_yuRr2AoCoZyA&key=AIzaSyADLqCeJAQo6qES8aNsfGH2n8fRjOAAMrQ",
      "https://maps.googleapis.com/maps/api/place/photo?maxwidth=400&photo_reference=AciIO2fKhW6W7yU1m91cTegMMMpHKWRUnWihILj0DqBpeVY7eGVuhGuxcAYE8gq0PGq8P1t76xDJWgvY8jr3j5baalxtbBUxsBAfa4vX_4cp_6rOS7d_szZLNpW-X2v-6c5ZqnQDm6qA5XEbdsDdp_Ey_3gI6Dp2onHC613WF9SdVps5arRdH-0gGu1Uk7-02_XQ31C7jlytPwWKH47LBi64DZbMlPAp8YFtEA4yOaz08aM2z08GvML0taJ8ek9JFEaHoE11v6raDfD5QneJ2S5jt8atY1S5vi3v4cSfxWJ4w78Dng&key=AIzaSyADLqCeJAQo6qES8aNsfGH2n8fRjOAAMrQ",
      "https://maps.googleapis.com/maps/api/place/photo?maxwidth=400&photo_reference=AciIO2cOeXBSpJyhbARNDuPDeRfvgv_RumclsgTcEn4IL6I9gqhKUzfrrPpmc9cgtrDVqaN84t3HiQc4tFeC1SveuVDIHiYp5wjJo4nMOLs0r9JqKSSry9J-_aHagw952ueig0dwlcO5GkGAJuwrWAKVdhCGhFrBypuotTzsISghWl-TOIjrrkqgw7gS5vCOK9H3h9r7Unol3wma-sw-5oLuuFoJ45eisZluLpKX_j-WwFpZiLkQDA7_cPQJHZYztueHO4tN3oS2VF3fiqVJ1ZVSCSlhTI9scHzEncYCBx0mQX-WbHbWZpuj33oVCRiSz5T1iY6cmXaRbjq_Oq3upc1UcD0G03eXsDpgDE_TadFm51SArh6Sx5cHFTd8rpdEpHhcTS1kVVl4tjOy2XS-HQg98exBK20ARkdLFKlSw-FmWuz0BQ&key=AIzaSyADLqCeJAQo6qES8aNsfGH2n8fRjOAAMrQ",
      "https://maps.googleapis.com/maps/api/place/photo?maxwidth=400&photo_reference=AciIO2dHgaNmdk6NCT6-W-ccc6MRYfvvZpl1h7IA9N_mVu6Sd18QIJXMeRSm8qubdmwS2x7f-U9PkSF739ZLcUzSPKA1wybGMpUfKO7AkDv4bRxF8JsfTHIwpJJy2bl4hOqT7kdJzgZOTYwYSSh9UYSORGCdd8ziKR27x8DeFG1kxw4FckXUPdXNORJzuliGntryMYU0PJ9s_5JxLpNWgWCg9WrbiUeS_hsb_Y6UQfc5Nd7c81kxf-L4aGgv3HGiBJZSrarxyGoBY9HTJXBgQ3lZENRYSWH7UBJMeOyCYyM_9XenBBWK_xfH4WV1x_TgUDCfmQhN6SxQ_gxzkKmscgHbtV_vbEmaVJ7AfwuF-XkQhD117HVkU0a7_-1LoBiGPVYGh9bBPJKkRzZ6zWY7Vnv1_nNgp8EppqbYwKHipfMtFp8&key=AIzaSyADLqCeJAQo6qES8aNsfGH2n8fRjOAAMrQ",
      "https://maps.googleapis.com/maps/api/place/photo?maxwidth=400&photo_reference=AciIO2dFqswQJTM1vEbthakyEE1XfDo57OqIHoNwMWCXoYT78UXqm2vz9BPdY9inrfLoXlL8HsbwsDfaWW2clKR0HqcbREYpMOyymfo2KIpgSSfkMpZrri3o5Namd_4CgTZDBcDEPZMAbKDuiJTS2qDDZky13-rgRxIFv3M-MTisPSYSm511_sA2njoywTdCEsHz7HODHQ7ofmCMB--Ymami-zIcqxKWqHzQt8FCG4dnnR57mL0RxXrqBOgURwb5NwAMzhzLK4Ob8LRd3MlDh3y7bBGIYIdZ2DDJn4VvXhLywx5Fkgr8ccOjBcFRviheBiTVtgH2q1w-tw3G2s5X_k7jpWfTVVPxY9gfl73gGCI78fBRT3MQM1Vz726GOLq-bLy1CjgbZ0rg6JdEXz09GNpj3Znn1WOnQplD04y5_OQuRYMWqNl3&key=AIzaSyADLqCeJAQo6qES8aNsfGH2n8fRjOAAMrQ",
      "https://maps.googleapis.com/maps/api/place/photo?maxwidth=400&photo_reference=AciIO2f-9hPB8mwl0ah2lGPKMPZGpwiHl0ngw_jrdIm6g-w4Iv33HZv_GsSNActUI-sfbROpeovRxgoXj0kEGfPIKBC50lQvEqNg7iyQkLMX46LRzUxWg_ZzUdEyvMIhUNGvHzXu3eTB5hdWz8bYgHn7me9oXjsSi7RJpCSmHs81fAOzPohEuPjzq7M3VuxDYRi8EoKpzgwrHtjsJ5Kkb22oq-d8dMeoj0FfPvqDoxJlBi9PmQKJvvivhpyZPhLJvruGcmAQPVSmkgBPb7Q1JuVhteFDKqSGaeo608GvZaDajVTkDiiDI0TnRviXJIU51Md9D2o9zsuAUXbUikXJHR0TcMA6VXJubGW5AaEEbIqL4MVLeU8x0tDQZrng156bqvM2KV6gqYHR5AsUel10eKu8L9lD0fN5ADTM1YHjULcLwuBH6hY&key=AIzaSyADLqCeJAQo6qES8aNsfGH2n8fRjOAAMrQ",
      "https://maps.googleapis.com/maps/api/place/photo?maxwidth=400&photo_reference=AciIO2fu9hrGZw2UTUBnM6SMrsyokuuf53GQ0Dqbi37yaHmuU93Zu3vMiG9mkt2mC53msk6PE2fg2wgFx1trcrn6U79XDO6bQpLFYNu9m_Ax03SYjkzSmXjiFrEM7w5kuK81lU2a6OUUfugwRLO5hvZLvibtx9t6SAT5xT55oR0tJ-HzascDvvxBBdTEqPOlBz5O2xCQJ6Fbw_IJHhnn4YjxSt5T8h73u7gGCHQ8MSht1B06Qeukf0Kn_6lJTW8rkFVRMsIeKfO0T-g8vDWX9NEeGgDduUqrhMDdn4_tJP859rc9ag&key=AIzaSyADLqCeJAQo6qES8aNsfGH2n8fRjOAAMrQ",
      "https://maps.googleapis.com/maps/api/place/photo?maxwidth=400&photo_reference=AciIO2eEoBC4iSVNqxNj2oCq_il4AuF8oQQFglECoxJ68TF7ylif3-HskIfgD0j-12Eo8-2r0Yu3ToiI6BT1dtEa1IoGr9xNXTe6oLrsZsLdSRY13AyapMJh5CFj1HIgpkL5wInLZaaR8qTTEuBVnIe_zPI2ptMs0Wp_gdgXfqXL_MDhSUav8n4aPky3I3I5u66zgsaa3f3s7HHdv2W1kO5fcpf923OdGgrbY6kJcneOquymkvwbE2Qj4jesUg5voeB45YG7SFssddhUZixpEbvCl_9xGJBY2XHXVE_7giVIRgAnAA&key=AIzaSyADLqCeJAQo6qES8aNsfGH2n8fRjOAAMrQ",
      "https://maps.googleapis.com/maps/api/place/photo?maxwidth=400&photo_reference=AciIO2cztxm7s9a1k-kKixg0RCLmgKzppvlOM23-4tKq35-e8Mdrj3gFVsl1d0T2TI1Ai3jL8b_W3tUpDPZqyG0jiHLSfvloqeO5F6vBoUtaJlmWOmiIMckaRyKknLFooLRFN5phUQ732NH6pDp9Ij_A_cwHscQyNZs86BZyN116B8Wt5zf3_h2o0QhLaVvYRFNrbtsruOMSm2NCTOLircx3n9emlVbmJN_wowBYVCHM1x_KJvYH-GWn9dVVvSUaYvUUclPLDRE1awYhiPfpVhkoCIfd7UZxKlsooX_frtr1jef7fA&key=AIzaSyADLqCeJAQo6qES8aNsfGH2n8fRjOAAMrQ"
    ],
    "mobileExperience": {
      "score": 66,
      "loadTime": 0,
      "isResponsive": true,
      "touchFriendly": true,
      "textReadable": true,
      "navigationEasy": false,
      "issues": [
        "Mobile performance data unavailable - API configuration required"
      ],
      "recommendations": [
        "Configure Google PageSpeed Insights API for mobile analysis",
        "Enable mobile performance monitoring",
        "Test website on mobile devices manually"
      ]
    },
    "reviewsAnalysis": {
      "overallScore": 92,
      "totalReviews": 454,
      "averageRating": 4.6,
      "sentimentBreakdown": {
        "positive": 100,
        "neutral": 0,
        "negative": 0
      },
      "reviewSources": [
        "Google Business Profile (Limited)"
      ],
      "keyThemes": [
        "Food Quality",
        "Service",
        "Pricing"
      ],
      "recentReviews": [
        {
          "author": "Steven Morgan",
          "rating": 5,
          "text": "Outstanding pizza and wings.  Service was great, a perfect low key place gather with good food",
          "date": "2025-08-10T15:46:07.000Z",
          "platform": "Google Places"
        },
        {
          "author": "Brian M.",
          "rating": 5,
          "text": "Have gotten pizza a number of times and always good. They have some unique choices that change with time. Picked up a deluxe sub tonight and it was good. Nothing terribly wild or exceptional but a good solid sub. Friendly service.",
          "date": "2025-08-05T23:01:05.000Z",
          "platform": "Google Places"
        },
        {
          "author": "Ali Nurmikko",
          "rating": 5,
          "text": "We just moved to the area from GR and this has been a go-to for us! After being heavily spoiled with the food scene, we were worried about moving to a small town with less options. MI Farmhouse did not disappoint!!! Delicious pizza! Great specialty pizza flavors. We have only done carry out, but its been great!",
          "date": "2025-08-01T16:11:32.000Z",
          "platform": "Google Places"
        },
        {
          "author": "Russell F",
          "rating": 5,
          "text": "I am in love with this Crab Rangoon Pizza.   It is a must try.\n\nMust update!  6/25. I just had their gluten free pizza crust.  Wow!  It tastes just like a regular flour crust.",
          "date": "2025-06-08T22:43:17.000Z",
          "platform": "Google Places"
        },
        {
          "author": "Abby Bailey",
          "rating": 5,
          "text": "Michigan Farmhouse Pizza, Thank you for carrying my favorite drinks right now! I love that you support local breweries!  (Long Road) And better priced than Meijer. The Elk Sausage Pizza is the bomb! Keep up the great work!\n\nI have been ordering from Farmhouse for the last 3 years or better, and I have always enjoyed their Pizza, Subs and Wraps! Never had a bad experience, if something was wrong, I’d call and they would make it right. Great customer service.",
          "date": "2024-11-03T00:54:16.000Z",
          "platform": "Google Places"
        }
      ],
      "examples": {
        "positive": [
          {
            "author": "Steven Morgan",
            "rating": 5,
            "text": "Outstanding pizza and wings.  Service was great, a perfect low key place gather with good food",
            "date": "2025-08-10T15:46:07.000Z",
            "platform": "Google Places"
          },
          {
            "author": "Abby Bailey",
            "rating": 5,
            "text": "Michigan Farmhouse Pizza, Thank you for carrying my favorite drinks right now! I love that you support local breweries!  (Long Road) And better priced than Meijer. The Elk Sausage Pizza is the bomb! Keep up the great work!\n\nI have been ordering from Farmhouse for the last 3 years or better, and I have always enjoyed their Pizza, Subs and Wraps! Never had a bad experience, if something was wrong, I’d call and they would make it right. Great customer service.",
            "date": "2024-11-03T00:54:16.000Z",
            "platform": "Google Places"
          },
          {
            "author": "Brian M.",
            "rating": 5,
            "text": "Have gotten pizza a number of times and always good. They have some unique choices that change with time. Picked up a deluxe sub tonight and it was good. Nothing terribly wild or exceptional but a good solid sub. Friendly service.",
            "date": "2025-08-05T23:01:05.000Z",
            "platform": "Google Places"
          }
        ],
        "neutral": [],
        "negative": []
      },
      "customerMoodAnalysis": {
        "overallMood": "delighted",
        "sentimentSummary": "Customers are genuinely thrilled with their experience. With an average 5.0/5 rating across 5 recent reviews, your restaurant consistently exceeds expectations.",
        "sentimentDistribution": {
          "ecstatic": 20,
          "delighted": 80,
          "satisfied": 0,
          "neutral": 0,
          "frustrated": 0,
          "disappointed": 0,
          "angry": 0
        },
        "keyMoodIndicators": [
          {
            "theme": "food quality",
            "mentions": 3
          },
          {
            "theme": "service excellence",
            "mentions": 1
          }
        ],
        "emotionalBreakdown": {
          "joy": 2,
          "satisfaction": 10,
          "disappointment": 0,
          "frustration": 0,
          "anger": 0
        },
        "businessInsights": {
          "strengthsPerceived": [
            "Customers love the unique and specialty pizza flavors, such as the Elk Sausage Pizza and Crab Rangoon Pizza, which keep them coming back for more. - social media marketing can showcase this strength",
            "The restaurant's commitment to supporting local breweries and offering favorite drinks at competitive prices is highly appreciated by customers. - SEO services can leverage this for better visibility",
            "Consistently friendly and responsive customer service, with a willingness to correct any issues, has built strong customer loyalty over the years. - review management can highlight this positive aspect"
          ],
          "improvementOpportunities": [
            "Maintain current high standards",
            "Continue engaging with customer feedback",
            "Monitor reviews for improvement opportunities"
          ]
        },
        "detailedMetrics": {
          "totalReviews": 5,
          "averageRating": 5,
          "ratingDistribution": {
            "1": 0,
            "2": 0,
            "3": 0,
            "4": 0,
            "5": 100
          },
          "sentimentTrends": {
            "trend": "stable",
            "recentAverageRating": 5,
            "previousAverageRating": 5,
            "recentReviewsCount": 5
          }
        }
      },
      "trends": {
        "ratingTrend": "positive",
        "volumeTrend": "increasing",
        "responseRate": 75,
        "averageResponseTime": "2 days"
      },
      "recommendations": [
        {
          "category": "growth",
          "priority": "high",
          "title": "Generate More Reviews",
          "description": "Encourage satisfied customers to leave reviews",
          "impact": "Increase online credibility and visibility"
        }
      ],
      "googleReviews": {
        "reviews": [
          {
            "author": "Steven Morgan",
            "rating": 5,
            "text": "Outstanding pizza and wings.  Service was great, a perfect low key place gather with good food",
            "date": "2025-08-10T15:46:07.000Z",
            "platform": "Google Places"
          },
          {
            "author": "Brian M.",
            "rating": 5,
            "text": "Have gotten pizza a number of times and always good. They have some unique choices that change with time. Picked up a deluxe sub tonight and it was good. Nothing terribly wild or exceptional but a good solid sub. Friendly service.",
            "date": "2025-08-05T23:01:05.000Z",
            "platform": "Google Places"
          },
          {
            "author": "Ali Nurmikko",
            "rating": 5,
            "text": "We just moved to the area from GR and this has been a go-to for us! After being heavily spoiled with the food scene, we were worried about moving to a small town with less options. MI Farmhouse did not disappoint!!! Delicious pizza! Great specialty pizza flavors. We have only done carry out, but its been great!",
            "date": "2025-08-01T16:11:32.000Z",
            "platform": "Google Places"
          },
          {
            "author": "Russell F",
            "rating": 5,
            "text": "I am in love with this Crab Rangoon Pizza.   It is a must try.\n\nMust update!  6/25. I just had their gluten free pizza crust.  Wow!  It tastes just like a regular flour crust.",
            "date": "2025-06-08T22:43:17.000Z",
            "platform": "Google Places"
          },
          {
            "author": "Abby Bailey",
            "rating": 5,
            "text": "Michigan Farmhouse Pizza, Thank you for carrying my favorite drinks right now! I love that you support local breweries!  (Long Road) And better priced than Meijer. The Elk Sausage Pizza is the bomb! Keep up the great work!\n\nI have been ordering from Farmhouse for the last 3 years or better, and I have always enjoyed their Pizza, Subs and Wraps! Never had a bad experience, if something was wrong, I’d call and they would make it right. Great customer service.",
            "date": "2024-11-03T00:54:16.000Z",
            "platform": "Google Places"
          }
        ],
        "averageRating": 4.6,
        "totalReviews": 454
      }
    },
    "socialMediaLinks": {
      "facebook": "https://www.facebook.com/michiganfarmhousepizza",
      "instagram": "https://www.instagram.com/michiganfarmhousepizza",
      "twitter": null,
      "youtube": null,
      "tiktok": null,
      "linkedin": null
    },
    "profileAnalysis": null,
    "serpScreenshots": [],
    "restaurantSearchScreenshot": null,
    "calculatedScores": {
      "search": 68,
      "social": 100,
      "local": 84,
      "reviews": 92,
      "overall": 86
    },
    "originalScores": {
      "seo": 81,
      "overallScore": 70,
      "performance": 86,
      "userExperience": 76
    },
    "migratedAt": "2025-09-16T00:37:21.316Z"
  },
  "metadata": {
    "cachedAt": "2025-09-15T16:50:12.471Z",
    "expiresAt": "2025-10-15T16:50:12.471Z",
    "placeId": "ChIJE2jOcr1rGIgR1F-N2hZC5aQ",
    "restaurantName": "Michigan Farmhouse Pizza",
    "cacheVersion": "2.0.0"
  }
}