{
  "data": {
    "domain": "topcrustjupiter.com",
    "restaurantName": "TopCrust Jupiter Kitchen",
    "placeId": "ChIJHcvLWvTV3ogRuhXfThCi_G8",
    "overallScore": 80,
    "performance": 100,
    "seo": 58,
    "mobile": 44,
    "userExperience": 88,
    "issues": [
      {
        "type": "seo",
        "severity": "critical",
        "title": "🎯 Missing in Action: Zero SEO Strategy",
        "description": "Your restaurant is invisible to potential customers searching online. No keyword optimization detected.",
        "impact": "high",
        "effort": "medium",
        "icon": "🔍",
        "color": "orange",
        "urgency": "high",
        "businessImpact": "Missing out on 70% of customers who search online before visiting"
      },
      {
        "type": "performance",
        "severity": "critical",
        "title": "⚡ Speed Crisis: Customers Are Leaving",
        "description": "Performance score of 64/100 means customers wait too long. 53% abandon slow websites.",
        "impact": "high",
        "effort": "medium",
        "icon": "🐌",
        "color": "red",
        "urgency": "immediate",
        "businessImpact": "Lost orders from customers who abandon slow-loading pages"
      },
      {
        "type": "mobile",
        "severity": "critical",
        "title": "📱 Mobile Disaster: Customers Can't Order",
        "description": "Mobile performance data unavailable - API configuration required",
        "impact": "high",
        "effort": "medium",
        "icon": "📱",
        "color": "red",
        "urgency": "immediate",
        "businessImpact": "60% of restaurant orders come from mobile - this is costing you sales"
      }
    ],
    "recommendations": [
      {
        "title": "Improve website performance",
        "description": "Improve website performance",
        "impact": "medium",
        "effort": "medium",
        "category": "technical"
      },
      {
        "title": "Enhance social media presence",
        "description": "Enhance social media presence",
        "impact": "medium",
        "effort": "medium",
        "category": "marketing"
      }
    ],
    "keywords": [],
    "competitiveOpportunityKeywords": [
      {
        "keyword": "pizza near me",
        "position": 2,
        "searchVolume": 3600,
        "difficulty": 0,
        "intent": "local",
        "cpc": 0,
        "competition": 0,
        "opportunity": 75,
        "url": "https://topcrustjupiter.com/",
        "title": "Best Pizza in Jupiter, FL | TopCrust Jupiter Kitchen | Pizza ...",
        "description": null,
        "isNew": null,
        "isLost": null,
        "positionChange": null,
        "previousPosition": null
      },
      {
        "keyword": "pizza delivery Jupiter",
        "position": 4,
        "searchVolume": 90,
        "difficulty": 0,
        "intent": "transactional",
        "cpc": 0,
        "competition": 0,
        "opportunity": 75,
        "url": "https://topcrustjupiter.com/",
        "title": "Best Pizza in Jupiter, FL | TopCrust Jupiter Kitchen | Pizza ...",
        "description": null,
        "isNew": null,
        "isLost": null,
        "positionChange": null,
        "previousPosition": null
      },
      {
        "keyword": "best pizza Jupiter",
        "position": 3,
        "searchVolume": 390,
        "difficulty": 0,
        "intent": "commercial",
        "cpc": 0,
        "competition": 0,
        "opportunity": 75,
        "url": "https://topcrustjupiter.com/",
        "title": "Best Pizza in Jupiter, FL | TopCrust Jupiter Kitchen | Pizza ...",
        "description": null,
        "isNew": null,
        "isLost": null,
        "positionChange": null,
        "previousPosition": null
      },
      {
        "keyword": "pizza",
        "position": 3,
        "searchVolume": 2400,
        "difficulty": 0,
        "intent": "navigational",
        "cpc": 0,
        "competition": 0,
        "opportunity": 75,
        "url": "https://topcrustjupiter.com/",
        "title": "Best Pizza in Jupiter, FL | TopCrust Jupiter Kitchen | Pizza ...",
        "description": null,
        "isNew": null,
        "isLost": null,
        "positionChange": null,
        "previousPosition": null
      },
      {
        "keyword": "pizza places near me",
        "position": 3,
        "searchVolume": 140,
        "difficulty": 0,
        "intent": "local",
        "cpc": 0,
        "competition": 0,
        "opportunity": 75,
        "url": "https://topcrustjupiter.com/",
        "title": "Best Pizza in Jupiter, FL | TopCrust Jupiter Kitchen | Pizza ...",
        "description": null,
        "isNew": null,
        "isLost": null,
        "positionChange": null,
        "previousPosition": null
      },
      {
        "keyword": "pizza Jupiter Florida",
        "position": 4,
        "searchVolume": 50,
        "difficulty": 0,
        "intent": "navigational",
        "cpc": 0,
        "competition": 0,
        "opportunity": 75,
        "url": "https://topcrustjupiter.com/",
        "title": "Best Pizza in Jupiter, FL | TopCrust Jupiter Kitchen | Pizza ...",
        "description": null,
        "isNew": null,
        "isLost": null,
        "positionChange": null,
        "previousPosition": null
      },
      {
        "keyword": "pizza delivery near me",
        "position": 4,
        "searchVolume": 390,
        "difficulty": 0,
        "intent": "transactional",
        "cpc": 0,
        "competition": 0,
        "opportunity": 75,
        "url": "https://topcrustjupiter.com/",
        "title": "Best Pizza in Jupiter, FL | TopCrust Jupiter Kitchen | Pizza ...",
        "description": null,
        "isNew": null,
        "isLost": null,
        "positionChange": null,
        "previousPosition": null
      },
      {
        "keyword": "pizza open now",
        "position": 5,
        "searchVolume": 10,
        "difficulty": 0,
        "intent": "navigational",
        "cpc": 0,
        "competition": 0,
        "opportunity": 75,
        "url": "https://topcrustjupiter.com/",
        "title": "Best Pizza in Jupiter, FL | TopCrust Jupiter Kitchen | Pizza ...",
        "description": null,
        "isNew": null,
        "isLost": null,
        "positionChange": null,
        "previousPosition": null
      }
    ],
    "enhancedKeywordDiscovery": [],
    "competitiveGaps": [],
    "keywordAnalysis": {
      "targetKeywords": [],
      "rankingPositions": [],
      "searchVolumes": {},
      "opportunities": [
        "Competitors rank higher for delivery keywords",
        "Missing from \"best restaurant\" searches"
      ]
    },
    "domainRankedKeywords": [],
    "localCompetitorData": [],
    "localPackReport": {
      "summary": {
        "visibility_score": 38,
        "keywords_appeared": 3,
        "total_keywords": 8,
        "average_position": 2.3,
        "best_position": 1
      },
      "keyword_results": [
        {
          "keyword": "pizza near me",
          "found": false,
          "confidence": 0,
          "matched_fields": [],
          "competitors": [
            {
              "position": 1,
              "name": "Al Forno Jupiter",
              "address": "Jupiter, FL ",
              "website": "http://alfornopizzas.com/",
              "rating": 4.4,
              "reviews": 499
            },
            {
              "position": 2,
              "name": "Angelo's Italian Restaurant",
              "address": "Jupiter, FL ",
              "website": "https://www.bestangelospizza.com/menu",
              "rating": 4.4,
              "reviews": 602
            },
            {
              "position": 3,
              "name": "Cucina Jupiter",
              "address": "Jupiter, FL ",
              "website": "http://cucinajupiter.com/",
              "rating": 4.5,
              "reviews": 281
            }
          ]
        },
        {
          "keyword": "pizza",
          "found": false,
          "confidence": 0,
          "matched_fields": [],
          "competitors": [
            {
              "position": 1,
              "name": "Al Forno Jupiter",
              "address": "Jupiter, FL ",
              "website": "http://alfornopizzas.com/",
              "rating": 4.4,
              "reviews": 499
            },
            {
              "position": 2,
              "name": "Angelo's Italian Restaurant",
              "address": "Jupiter, FL ",
              "website": "https://www.bestangelospizza.com/menu",
              "rating": 4.4,
              "reviews": 602
            },
            {
              "position": 3,
              "name": "Blaze Pizza",
              "address": "Jupiter, FL ",
              "website": "https://locations.blazepizza.com/fl/jupiter/1697-w-indiantown-rd?utm_source=gmb&utm_medium=yext",
              "rating": 4.2,
              "reviews": 282
            }
          ]
        },
        {
          "keyword": "best pizza Jupiter",
          "found": true,
          "position": 1,
          "confidence": 100,
          "matched_fields": [
            "title",
            "url"
          ],
          "local_pack_data": {
            "name": "TopCrust Jupiter Kitchen",
            "address": "Jupiter, FL ",
            "website": "https://topcrustjupiter.com/?utm_source=google",
            "phone": "(561) 250-6523",
            "rating": 4.7,
            "reviews": 355
          },
          "competitors": []
        },
        {
          "keyword": "pizza delivery near me",
          "found": false,
          "confidence": 0,
          "matched_fields": [],
          "competitors": [
            {
              "position": 1,
              "name": "Al Forno Jupiter",
              "address": "Jupiter, FL ",
              "website": "http://alfornopizzas.com/",
              "rating": 4.4,
              "reviews": 499
            },
            {
              "position": 2,
              "name": "Angelo's Italian Restaurant",
              "address": "Jupiter, FL ",
              "website": "https://www.bestangelospizza.com/menu",
              "rating": 4.4,
              "reviews": 602
            },
            {
              "position": 3,
              "name": "Riko's Pizza",
              "address": "Tequesta, FL ",
              "website": "https://www.rikospizza.com/",
              "rating": 4.4,
              "reviews": 215
            }
          ]
        },
        {
          "keyword": "pizza Jupiter Florida",
          "found": false,
          "confidence": 0,
          "matched_fields": [],
          "competitors": [
            {
              "position": 1,
              "name": "Al Forno Jupiter",
              "address": "Jupiter, FL ",
              "website": "http://alfornopizzas.com/",
              "rating": 4.4,
              "reviews": 499
            },
            {
              "position": 2,
              "name": "Angelo's Italian Restaurant",
              "address": "Jupiter, FL ",
              "website": "https://www.bestangelospizza.com/menu",
              "rating": 4.4,
              "reviews": 602
            },
            {
              "position": 3,
              "name": "Tiramisù Pizzeria & Osteria",
              "address": "Jupiter, FL ",
              "website": "https://tiramisupizzeria.com/jupiter",
              "rating": 4.5,
              "reviews": 43
            }
          ]
        },
        {
          "keyword": "top pizza Jupiter",
          "found": true,
          "position": 1,
          "confidence": 100,
          "matched_fields": [
            "title",
            "url"
          ],
          "local_pack_data": {
            "name": "TopCrust Jupiter Kitchen",
            "address": "Jupiter, FL ",
            "website": "https://topcrustjupiter.com/?utm_source=google",
            "phone": "(561) 250-6523",
            "rating": 4.7,
            "reviews": 355
          },
          "competitors": []
        },
        {
          "keyword": "pizza restaurant near me",
          "found": false,
          "confidence": 0,
          "matched_fields": [],
          "competitors": [
            {
              "position": 1,
              "name": "Al Forno Jupiter",
              "address": "Jupiter, FL ",
              "website": "http://alfornopizzas.com/",
              "rating": 4.4,
              "reviews": 499
            },
            {
              "position": 2,
              "name": "Angelo's Italian Restaurant",
              "address": "Jupiter, FL ",
              "website": "https://www.bestangelospizza.com/menu",
              "rating": 4.4,
              "reviews": 602
            },
            {
              "position": 3,
              "name": "Carmine's Coal Fired Pizza",
              "address": "Jupiter, FL ",
              "website": "http://www.carminescfp.com/",
              "rating": 4.3,
              "reviews": 787
            }
          ]
        },
        {
          "keyword": "pizza food Jupiter",
          "found": true,
          "position": 5,
          "confidence": 100,
          "matched_fields": [
            "title",
            "url"
          ],
          "local_pack_data": {
            "name": "TopCrust Jupiter Kitchen",
            "address": "Jupiter, FL ",
            "website": "https://topcrustjupiter.com/?utm_source=google",
            "phone": "(561) 250-6523",
            "rating": 4.7,
            "reviews": 355
          },
          "competitors": [
            {
              "position": 1,
              "name": "Al Forno Jupiter",
              "address": "Jupiter, FL ",
              "website": "http://alfornopizzas.com/",
              "rating": 4.4,
              "reviews": 499
            },
            {
              "position": 2,
              "name": "Angelo's Italian Restaurant",
              "address": "Jupiter, FL ",
              "website": "https://www.bestangelospizza.com/menu",
              "rating": 4.4,
              "reviews": 602
            },
            {
              "position": 3,
              "name": "Tiramisù Pizzeria & Osteria",
              "address": "Jupiter, FL ",
              "website": "https://tiramisupizzeria.com/jupiter",
              "rating": 4.5,
              "reviews": 43
            }
          ]
        }
      ],
      "recommendations": [
        "Not appearing for \"pizza near me\", \"pizza\", \"pizza delivery near me\", \"pizza Jupiter Florida\", \"pizza restaurant near me\" - optimize Google My Business profile with these keywords",
        "Ranking below #1 for 1 keywords - increase customer reviews and engagement to improve rankings",
        "Low Local Pack visibility (38%) - audit your Google My Business completeness, categories, and local citations"
      ],
      "scan_metadata": {
        "location": "Jupiter,Florida,United States",
        "timestamp": "2025-09-15T16:10:20.243Z",
        "total_scan_time_ms": 44492
      }
    },
    "competitors": [
      {
        "name": "Guanabanas Restaurant",
        "domain": "guanabanasrestaurant.com",
        "performance": 88,
        "seo": 79,
        "accessibility": 75,
        "bestPractices": 84,
        "overallScore": 81,
        "rating": 4.4,
        "totalReviews": 0,
        "photos": {
          "total": 0,
          "quality": "fair"
        },
        "responseRate": 30,
        "isVerified": false,
        "isYou": false,
        "traffic": 1015,
        "keywords": 37,
        "domainAuthority": 71,
        "trafficAdvantage": "Similar traffic",
        "keywordLead": "Similar keywords",
        "authorityGap": 0,
        "backlinks": 1112
      },
      {
        "name": "The Woods Jupiter",
        "domain": "thewoodsjupiter.com",
        "performance": 86,
        "seo": 77,
        "accessibility": 73,
        "bestPractices": 82,
        "overallScore": 80,
        "rating": 4.3,
        "totalReviews": 0,
        "photos": {
          "total": 0,
          "quality": "fair"
        },
        "responseRate": 30,
        "isVerified": false,
        "isYou": false,
        "traffic": 908,
        "keywords": 44,
        "domainAuthority": 73,
        "trafficAdvantage": "Similar traffic",
        "keywordLead": "Similar keywords",
        "authorityGap": 0,
        "backlinks": 1126
      },
      {
        "name": "Dive Bar Restaurant",
        "domain": "divebarrestaurant.com",
        "performance": 90,
        "seo": 81,
        "accessibility": 77,
        "bestPractices": 86,
        "overallScore": 83,
        "rating": 4.5,
        "totalReviews": 0,
        "photos": {
          "total": 0,
          "quality": "fair"
        },
        "responseRate": 30,
        "isVerified": false,
        "isYou": false,
        "traffic": 1187,
        "keywords": 24,
        "domainAuthority": 87,
        "trafficAdvantage": "Similar traffic",
        "keywordLead": "Similar keywords",
        "authorityGap": 0,
        "backlinks": 708
      },
      {
        "name": "Little Moir's Food Shack",
        "domain": "littlemoirsfoodshack.com",
        "performance": 96,
        "seo": 86,
        "accessibility": 82,
        "bestPractices": 91,
        "overallScore": 89,
        "rating": 4.8,
        "totalReviews": 0,
        "photos": {
          "total": 0,
          "quality": "fair"
        },
        "responseRate": 30,
        "isVerified": false,
        "isYou": false,
        "traffic": 635,
        "keywords": 29,
        "domainAuthority": 90,
        "trafficAdvantage": "Similar traffic",
        "keywordLead": "+50 keywords",
        "authorityGap": 1,
        "backlinks": 764
      },
      {
        "name": "1000 NORTH",
        "domain": "1000north.com",
        "performance": 92,
        "seo": 83,
        "accessibility": 78,
        "bestPractices": 87,
        "overallScore": 85,
        "rating": 4.6,
        "totalReviews": 0,
        "photos": {
          "total": 0,
          "quality": "fair"
        },
        "responseRate": 30,
        "isVerified": false,
        "isYou": false,
        "traffic": 561,
        "keywords": 25,
        "domainAuthority": 85,
        "trafficAdvantage": "Similar traffic",
        "keywordLead": "Similar keywords",
        "authorityGap": 0,
        "backlinks": 808
      }
    ],
    "competitorIntelligence": {
      "organicCompetitors": [],
      "keywordGaps": [
        "best pizza delivery",
        "pizza restaurant online ordering"
      ],
      "trafficEstimates": []
    },
    "serpFeatures": [],
    "domainAuthority": 67,
    "screenshot": null,
    "seoAnalysis": {
      "title": "No title found",
      "metaDescription": "No meta description found",
      "h1Tags": [],
      "imageCount": 0,
      "internalLinks": 0,
      "externalLinks": 0,
      "schemaMarkup": false
    },
    "metrics": {
      "fcp": 0,
      "lcp": 0,
      "cls": 0,
      "fid": 0
    },
    "backlinks": 0,
    "organicTraffic": 0,
    "scanDate": "2025-09-15T16:10:31.036Z",
    "businessProfile": {
      "name": "TopCrust Jupiter Kitchen",
      "address": "3755 Military Trail Suite B8, Jupiter, FL 33458, USA",
      "rating": 4.7,
      "reviewCount": 355,
      "phoneNumber": "(561) 250-6523",
      "website": "https://topcrustjupiter.com/?utm_source=google",
      "formatted_address": "3755 Military Trail Suite B8, Jupiter, FL 33458, USA",
      "address_components": [
        {
          "long_name": "Suite B8",
          "short_name": "Suite B8",
          "types": [
            "subpremise"
          ]
        },
        {
          "long_name": "3755",
          "short_name": "3755",
          "types": [
            "street_number"
          ]
        },
        {
          "long_name": "Military Trail",
          "short_name": "Military Trail",
          "types": [
            "route"
          ]
        },
        {
          "long_name": "Jupiter",
          "short_name": "Jupiter",
          "types": [
            "locality",
            "political"
          ]
        },
        {
          "long_name": "Palm Beach County",
          "short_name": "Palm Beach County",
          "types": [
            "administrative_area_level_2",
            "political"
          ]
        },
        {
          "long_name": "Florida",
          "short_name": "FL",
          "types": [
            "administrative_area_level_1",
            "political"
          ]
        },
        {
          "long_name": "United States",
          "short_name": "US",
          "types": [
            "country",
            "political"
          ]
        },
        {
          "long_name": "33458",
          "short_name": "33458",
          "types": [
            "postal_code"
          ]
        }
      ],
      "state": "Florida",
      "city": "Jupiter",
      "place_id": "ChIJHcvLWvTV3ogRuhXfThCi_G8",
      "business_status": "OPERATIONAL",
      "types": [
        "establishment",
        "food",
        "meal_delivery",
        "meal_takeaway",
        "point_of_interest",
        "restaurant"
      ],
      "reviews": [
        {
          "author_name": "Van E. Singelis (VMAN)",
          "author_url": "https://www.google.com/maps/contrib/102969671570495005665/reviews",
          "language": "en",
          "original_language": "en",
          "profile_photo_url": "https://lh3.googleusercontent.com/a-/ALV-UjWqgKSmE8mcnZIHfYTgrAhpONbZMWNvz3xZ7sPOGDGTX_li-D-7_g=s128-c0x00000000-cc-rp-mo",
          "rating": 5,
          "relative_time_description": "2 months ago",
          "text": "Ordered the special large pizza with 10 hot wings!\nOh Mama.... Crispy golden crust, fresh ingredients, savory mushrooms with just the right amount of pepperoni.  Not to saucy, and the perfect complement of cheese.  Chicken wings extra crispy, bold, tangy, spicy and flavorful.\nJeff the owner and his kitchen staff always make you feel at home.  Give them a try, tell Jeff the VMAN sent you.  Oh did I mention the homemade cannoli's, HUGE!",
          "time": 1752249401,
          "translated": false
        },
        {
          "author_name": "Alice Djubin",
          "author_url": "https://www.google.com/maps/contrib/101226160057692887735/reviews",
          "language": "en",
          "original_language": "en",
          "profile_photo_url": "https://lh3.googleusercontent.com/a/ACg8ocKVxTPt_g_UjXtrVP90Ir8mDx_DQCDqWK2vIz-gvcSBq2RU=s128-c0x00000000-cc-rp-mo",
          "rating": 5,
          "relative_time_description": "3 weeks ago",
          "text": "Excellent pizza presentation with a generous amount of toppings evenly distributed across the pie. I placed a takeout order and it was ready a good 5 minutes before the estimated pickup time. Employees were pleasant and courteous. The pie was absolutely delicious!  This was my second time ordering and this store is now my go-to place for delicious pizza. I have already recommended Top Crust to my friends and neighbors. Thank you and keep up the great work!",
          "time": 1756050268,
          "translated": false
        },
        {
          "author_name": "David N",
          "author_url": "https://www.google.com/maps/contrib/111266317467504450780/reviews",
          "language": "en",
          "original_language": "en",
          "profile_photo_url": "https://lh3.googleusercontent.com/a/ACg8ocJS-rX8pQ3ESXHtJiUubdz1hO4SDOJhQy8WB6U3AN34TUAFkg=s128-c0x00000000-cc-rp-mo-ba2",
          "rating": 5,
          "relative_time_description": "2 weeks ago",
          "text": "Wow!  That’s the best pizza I’ve had in a very long time. Delicious. Excellent customer service.\nI’m impressed",
          "time": 1756691786,
          "translated": false
        },
        {
          "author_name": "Christine Rowell",
          "author_url": "https://www.google.com/maps/contrib/101436700792490495996/reviews",
          "language": "en",
          "original_language": "en",
          "profile_photo_url": "https://lh3.googleusercontent.com/a-/ALV-UjVtUE2bPoa3U0xy4eXYVfiJUCPGVZ3EBpjK6sYYpVeE_Y75gw-UzQ=s128-c0x00000000-cc-rp-mo",
          "rating": 5,
          "relative_time_description": "a month ago",
          "text": "Food was delicious! We got delivery so that’s the only reason the pizza was a little mis shaped! Tip would be tip wrap the rolls also with clear wrap to keep all the goodness in with them!",
          "time": 1753308952,
          "translated": false
        },
        {
          "author_name": "Chelsey Steinarsson",
          "author_url": "https://www.google.com/maps/contrib/103983948256017729516/reviews",
          "language": "en",
          "original_language": "en",
          "profile_photo_url": "https://lh3.googleusercontent.com/a/ACg8ocLTDtOo6XMoMoJIsg3RMlOO6yiVtfFTt_tYBWKOHIYMLSXqIA=s128-c0x00000000-cc-rp-mo",
          "rating": 5,
          "relative_time_description": "2 weeks ago",
          "text": "Top Crust has fantastic pizza! They have gluten free and cauliflower crust options that actually taste really good!!! They have several specialty combinations and their wings are delicious! Every time we order the food is hot and fresh. You must try them!",
          "time": 1756597926,
          "translated": false
        }
      ],
      "photos": [
        {
          "height": 4032,
          "html_attributions": [
            "<a href=\"https://maps.google.com/maps/contrib/107046013059987868164\">TopCrust Jupiter Kitchen</a>"
          ],
          "photo_reference": "AciIO2cK3wJQ1L7u5zQyd-FBe4nJ8oDidtOJClZGCzwcpLXI2GaULYOgTbjscOWtQGnOCNnvojPjnTVBkGiuah86f9M5vsfqMBSBB-ienY4M4MhM1olS_u7UnBbxu3fphZxh10AW_Lj26Vdsu_xSSRHT0lXuGqCt26X5ZDH0bA1VDatocn2B_9K3kVpUk92C0RlF1aSza2RqywrEfQCiJb0VkTEAigQ9BWgmR_9guJIrXrll5gYDd_cpmClVOqjMslEmYoRIqJVmrOs_gOcHCqlmospgfXufFuvv85_-cpO6_ANctg",
          "width": 3024
        },
        {
          "height": 4032,
          "html_attributions": [
            "<a href=\"https://maps.google.com/maps/contrib/107046013059987868164\">TopCrust Jupiter Kitchen</a>"
          ],
          "photo_reference": "AciIO2cSUVWLkXhdZPPJ1Ny4utPk9I5BkRSk0D_KWL0iOn1ijJG9C_p8J3Ep7d5cgZpWiXlvmtbh0hggWVzFXaNguXayhErjcYMqcYhsobfqqVpaiisdLw9390AeMZRArdQuWDnDcQkEjjJ49rjivHdBPJEV62NfCyOIrHv2IP3rIEOUPS5elHGTTyDOBVEP4cRY_X5rRdyoVfoWKmJXi6W4xhuycubzRaYnu1LEWvdnMpsOnZMXQl1J8-iPvMBBSdgMlp8WOtHw68NYKQDSCQa9nL3te62nBnj43NNEFjXXesReMA",
          "width": 3024
        },
        {
          "height": 4032,
          "html_attributions": [
            "<a href=\"https://maps.google.com/maps/contrib/107046013059987868164\">TopCrust Jupiter Kitchen</a>"
          ],
          "photo_reference": "AciIO2dP3N_-PtrPVqJHaI8MA6Z4xDEeuXUQGLPEr3VP5qzdvKsdRUIJPTK4xMw2ephEexJhbcoyS7ScSZSOfiOOhpSkvUbcywOHeD673i67hQBGZ9mVwc39Qn8EYM0q7rlyRjGyrGZFdj9ZcjHx9ud-QhDjSpf9wNoQtoOtTAQYEfJ1JqIz8J_hDRmOfsdxGx_q0mdS8JPpFaqp1FS8zEZnFGsZl6X_-5zdo2fxp5Pa7xLH8c9GNz6TfZOc90wrKkgubLYrNEgeINghaJwknih3uVrNqfuseOp8yxR2lSu2lMVRtw",
          "width": 3024
        },
        {
          "height": 4032,
          "html_attributions": [
            "<a href=\"https://maps.google.com/maps/contrib/107046013059987868164\">TopCrust Jupiter Kitchen</a>"
          ],
          "photo_reference": "AciIO2fu96k_BUHd6u-zfP6CNR8JOVJOntljhz_ZpVaLgQaqblSLZMka9--hcmAHF_ppc9c82uV73VFSF52iC_Cy0Paoc1T6aqj8LvsTQUXkuIgLAgEaoWGp3Ie6dZZm_krSncmzdmNqFR0Tzjc0-Iwo4skKf2lMm_4gbY1rPiBH6Lhe9fCIqSR4jFPDk0rORHh9lpWR9e2cvwEh1bm0E6jImYYEfUSXDiDD18oSRyIjDrI-TuFXFQOXi8mw_Sb_EEGqBFL-r-l959uIXkY-XSU40pvUX8i0MGGWDoe8rMbktCfgeg",
          "width": 3024
        },
        {
          "height": 3000,
          "html_attributions": [
            "<a href=\"https://maps.google.com/maps/contrib/117827967903642575669\">Howie Alli</a>"
          ],
          "photo_reference": "AciIO2d3OwmCuwYDo4YiOONM2IvzAGHGc_2YmeQS9pPa53Pj5ApH-kF2LSj1LbYey-oktVEWFFJn1lgcpAUGsocb7217DBB4iFcDhXs_LWy1ljVIA4FlGM2AiD1Y1Ju2o-8_8XxNMTNyPrYpYKSGTy1e49vQ2GxFndlhm04Bs3Z3eZmHsG06RGVMl5N5qPt9v2H_MOqoZ__NBRcrGhdWWMsXDUzCnFQJ3T2It5605bURJ9GbUzkauo0v1NKgu2ga5nKRABjy2-Nmm_y2kRb9TgfnEa9_QbJK3QXpt4K9jqkB54b182UteBTKXJhjXBmnhvSrS7LsPM0ZftIdITKWNRue0PqN9Dycvb_fkX9VPzxrq34Da-cmW6SSnEI3LfcomAHGNEHK0Oftn_k4cObo4eQk3QnEftMHUpVCue-LQJvjNJGRVA",
          "width": 4000
        },
        {
          "height": 4032,
          "html_attributions": [
            "<a href=\"https://maps.google.com/maps/contrib/107046013059987868164\">TopCrust Jupiter Kitchen</a>"
          ],
          "photo_reference": "AciIO2d4fnOJSa2tpXSSBQy9o7n1oHo_PrrraqxENaOrMpN-PKSmXABaQgISoolDYFBZIqiO4mZsYdYF3BbwFIM-yplChGFfdYFONk6HxVnwES46kB1495ey2z6JP2mzDblE3If_crjy098poFXuJz3KVf9vnBSiDjr2r3ijoX_FaaTwIDYj5xSL-fQZ-aTWYLy0r_towYPKVu-RbZ-j7_AdTyF3ETq3sK8-HUpAorRiNVAIGFBlZ6sPFq7rhB679ppJx4Z_7bjBKFrUPw5oZQwX5fcwbg6r00LIQWC505pvzkgXEw",
          "width": 3024
        },
        {
          "height": 4032,
          "html_attributions": [
            "<a href=\"https://maps.google.com/maps/contrib/107046013059987868164\">TopCrust Jupiter Kitchen</a>"
          ],
          "photo_reference": "AciIO2fXGesQC9vU_j_SNwdpJqFnkcwllPLDZYlXP00Kei0HEReYvIm42yMprxhe6kJ5KkGq-SNL6dUlPeBF79Kd140Zg9tGvCjYra5AC-PG1DVDH-YVd4BBM8DttITPBDNxHEH70eGbODninB8SktQy-WueEgoUDaQbz6NubTZuLbpFrqZL-HrpDtD6O6JjDn9ihPQ2JQlY_X-Y4a9XCG0CJiBnaNUSmcA9vpBPgqXFuBncaJHfQk8RjG3XKJe_aVA9EOXobkRKd7G4g7QP3zQ3niqiDPXcANgMdb-H_1ElLgcD2w",
          "width": 3024
        },
        {
          "height": 4032,
          "html_attributions": [
            "<a href=\"https://maps.google.com/maps/contrib/107046013059987868164\">TopCrust Jupiter Kitchen</a>"
          ],
          "photo_reference": "AciIO2f3bda7-x3LbDSRC429mvAs3zn3ej7w6kXv5Qi6FYq5QLSqkaEl-Exrxf1HGL1ZoY2SBn8szxE3181jB2FSjjL5aiK3gcFWrjNX1hs128Bb4LyGGGc6eHRsRRkntcU_pOquWTVGXANzXKI92BfqO_Q4sHp7TqcsFERW7S7Z6hbB997nd2YH-A4W-OT1jOMn-_b2wPbEoYxstL-K9_blYLuLZlwN--R-zkOOLwbvwCcWxGfDtklKo3aGIe-KRhqCIxmgwik_sQOO_gCxcpUWtXC08SCir-zwaZQNqIm7FMW6QQ",
          "width": 3024
        },
        {
          "height": 4032,
          "html_attributions": [
            "<a href=\"https://maps.google.com/maps/contrib/107046013059987868164\">TopCrust Jupiter Kitchen</a>"
          ],
          "photo_reference": "AciIO2cZ67JV9vc89ar2gbKiQYEckww-jtBJQr5TLwTdjGT0IhPkXBEQeqWg26kxxQcD8e_e7pt6TSOqjxAmNw0OBAqUJxSebH6QDzXdaNntbz1Ny7YuTaQbir_M6-eCXfv2UFhNIQLhKx_EL_LAgYet-1XuM_ZIZ5kvaIa81flo5J42pyEzLaD1q9eRJpEyYMIRagIvGez7Ho6NTbrQVwFqFP_eGkYj77O0z1cvKyPLB0mJelsgLRz1W-d1RnvdMmedMIsj9MoHT1qaXor6HNKXrZRmqtOuB5sDiwZ26HR5t8nZkQ",
          "width": 3024
        },
        {
          "height": 4032,
          "html_attributions": [
            "<a href=\"https://maps.google.com/maps/contrib/107046013059987868164\">TopCrust Jupiter Kitchen</a>"
          ],
          "photo_reference": "AciIO2fLPsoOjuY7XeF0CRQVTOLkfTz5nA70iLRkYpG4ZOHA_vHpyHpG67IgxepyGOYkDDpVj2-LEIEM01Mc7wR_Z8MpgzrB_99P5SftkrGML9B5MU773sRto7xHyDyxJ7KSYE507wCt1DqMZ_cvdjOrcLCsIbYH2xt9dOYsr9j1-UFihu8qLpoIJziA6JP8-Db36_p20FtadgoVbCMM8r8psBPCXYs2l9wAlZGV3Vz8uPnJrr5t-l5F7lsyoZU2LVEqOwcDutiYRghnrd6x-4DRgd0JWPNLgzDUTy2kKvnejMiFVg",
          "width": 3024
        }
      ],
      "photoCount": 10,
      "opening_hours": {
        "open_now": false,
        "periods": [
          {
            "close": {
              "day": 0,
              "time": "2100"
            },
            "open": {
              "day": 0,
              "time": "1100"
            }
          },
          {
            "close": {
              "day": 2,
              "time": "2100"
            },
            "open": {
              "day": 2,
              "time": "1100"
            }
          },
          {
            "close": {
              "day": 3,
              "time": "2100"
            },
            "open": {
              "day": 3,
              "time": "1100"
            }
          },
          {
            "close": {
              "day": 4,
              "time": "2100"
            },
            "open": {
              "day": 4,
              "time": "1100"
            }
          },
          {
            "close": {
              "day": 5,
              "time": "2200"
            },
            "open": {
              "day": 5,
              "time": "1100"
            }
          },
          {
            "close": {
              "day": 6,
              "time": "2200"
            },
            "open": {
              "day": 6,
              "time": "1100"
            }
          }
        ],
        "weekday_text": [
          "Monday: Closed",
          "Tuesday: 11:00 AM – 9:00 PM",
          "Wednesday: 11:00 AM – 9:00 PM",
          "Thursday: 11:00 AM – 9:00 PM",
          "Friday: 11:00 AM – 10:00 PM",
          "Saturday: 11:00 AM – 10:00 PM",
          "Sunday: 11:00 AM – 9:00 PM"
        ]
      },
      "price_level": 2,
      "editorial_summary": null,
      "url": "https://maps.google.com/?cid=8069502823267505594",
      "social_media": null
    },
    "businessPhotos": [
      "https://maps.googleapis.com/maps/api/place/photo?maxwidth=400&photo_reference=AciIO2eDf0rCyheRkYBMhB4swLOshF8dxIf8mBgAc83RO-iEuqAYlNecaQPaGdnyosv6IKaRe8-HcGi-OylBrDPX_nCaaEXzKnfrvHpr32Gu8UvR0Xv58iZ6sfM4KFTEKwpNr9QmabJNMYOBMfr6Ne7LL9WOU3brBsgBxlxbgRyEg6JTjP21GIU-xFBvFmkfUQuCGI76KzVclPdnCSC0V938vyF-7HaBU6k45MfaDZqhcrdHUhdYIRN-N50L49yzDbzVCjqZi53j1oidO7IcNhNdUZ78ZgEmzgaBepJi7oEwYY4Kng&key=AIzaSyADLqCeJAQo6qES8aNsfGH2n8fRjOAAMrQ",
      "https://maps.googleapis.com/maps/api/place/photo?maxwidth=400&photo_reference=AciIO2f8i2uEw--IJ_q7RIenRsBpvWhi9M5w-ZGTji5S0C5pFrycKJ6VS0rlEGy4kY_Dh5kmKE58DmU-7bj1WU42vt2IZfs-X9GXiW0P4HVFx9aQK3RR5lA0ON0eR0CdXv5PQ8oiv5eDr_al3MRRNoxiPMJuQCI6NOJYwzQXWzLMY8JwyYxjt8laQA6F1qmYkCTC05fFIMoMxHnce_nun1DjGbtNzmrwUg7yzUuvQMNljnqfmf_gDWLlO15jaoikVVnvIuhM6ZJSUERL0bGKONOYcCZK1RbeGSTaPu-Ahi9xNSa13Q&key=AIzaSyADLqCeJAQo6qES8aNsfGH2n8fRjOAAMrQ",
      "https://maps.googleapis.com/maps/api/place/photo?maxwidth=400&photo_reference=AciIO2f-ub9GMFl-4IK85brCw5bHlsgjFPW7wcrwDFWbRP6a3w40n2pLwy1DIOZWJy-Ob8TxbxmCL3rycGU9jnurZRoSFvmMd0_Be2b3C525t5zv1bZlmCnWqp8CaD_4rhUKydi-Z0nDZRzRFRz35WfAx-xzUXjOPvnv5E2vZDNmQKk_fCTzEpqWXc4bVor-xyvkdhJ2hdPJL9dpiBOHpSbinXUhpZxhRNeFMwAzkvtCy0RWOlYbw2f1qeSs7EAZm9FK0ikI-fibIVrsBE_FPHozlbfjw1_VXb4dGiVqF6a9pQYH6w&key=AIzaSyADLqCeJAQo6qES8aNsfGH2n8fRjOAAMrQ",
      "https://maps.googleapis.com/maps/api/place/photo?maxwidth=400&photo_reference=AciIO2chNmCPAM_qQjNRGPiqPmx6nvG9HK6jIKx7IMrOwkqVppCfR5Rbce3QQ_QCyS7zYd1IM0Uk0f3yRvCL1c4MZvu1FXn3qMI6di_MKB56UFTlM5DsKGbkI_6gm0DR5SSp7_YPFoiVsGYX-zYcXqBETn1rWYffpQjblCQYZCvBED9trhgfK_PKa3nNBKNPkfvEcAt0f6GRqnvmL8Bf2HXTIhelmwsuw8jIAq01eFHvX5qJNaJelD1dceWbzOrzpWSp0hQGrZXI1xoW1cHtng0c7wWmMWz9mOAQ2FDTHbXrHe9NtQ&key=AIzaSyADLqCeJAQo6qES8aNsfGH2n8fRjOAAMrQ",
      "https://maps.googleapis.com/maps/api/place/photo?maxwidth=400&photo_reference=AciIO2cLVekwCCXLP1QbDF30JafNUJ2f6r1_RLKk_WjQdTr6tnnVKMcr5S9MFCH9PLqfxfpOwKiO1hAtVFqy8BZOxaQ6pu3-Kuqpod823JuiKjbjGYMJ2Y0b79EgN4zQYN1YRoo_jbCxS3i6M0G9U8r8pWDq_iHOqzRi-MGgEJHCv1CFKb-l1qXhrPQIrT-8MntuAu8k2Qgv-kLt7RgyrbgixrtMIXfCXMmKBM9lup4uLLYGB-cKf1dNqjVAO-P-Jm8pOAe7NccEqkhNTwaIALx0qhaHtCpO3i_95nCmZAY42wRS8Nx836MQvYdQvtNWnFQsSIXoLhn0JLg6SSR1aCfmaMAdPQWf85Kgo-WBGAI5U9gWnLXIgLX6n3F0sDUr6qOqsHP_z5gQa01WxqXEy9J88qDwB_fsOnNTQDQk4V6fyUYPJQ&key=AIzaSyADLqCeJAQo6qES8aNsfGH2n8fRjOAAMrQ",
      "https://maps.googleapis.com/maps/api/place/photo?maxwidth=400&photo_reference=AciIO2fkVmteUvAsGaDAEhaxhztZsdrbMcRDnFEPVA6q1qlIy-WGpv3pgeQbwtw5V3UhY6N_kjbrQ_CNQXmHFzztq_M0j4V5OErATKcwF8E1hkgnJDCK7kK2ysAFGziFpkpPxHluk0yG6UYWj8ez_kj6ikcEPObO8d86qk52KshYQmUswhD5dEWvM9eInHfX1dPjXGku1ZPjTT1CdDe7BkB7jeP5iuObyp-FK4s7y2yvz8Q67yRdVeuOorsvRhQIbWeIoKYDw0jG73_M3TuR3CDVJmPKhjRA37iFj6444RQl_k8lPw&key=AIzaSyADLqCeJAQo6qES8aNsfGH2n8fRjOAAMrQ",
      "https://maps.googleapis.com/maps/api/place/photo?maxwidth=400&photo_reference=AciIO2e1sseLJXGPZpDpuAqzx0TKqONekLu93emSODiCVG1pRWt2cJeiwKTj8Mj_hDgp4izm8WAJfBAXoDope95tI2Ul3Cy9sE-JO7gX2OLRhTgld680r19SfNQvCB-RQkIAQ805G2U08cZasYQEE950a2Z47ymYOzznf9bI9ReZrZG0VE8k1rhJCh-5Hh0vvfFVQKFLGwY7pJbqzQ_L7rmvCjFmhTFRdcxcXr-gffxcTsFZoqEhi2iGSkpJ2LHa07II8Aa1e0P2soTUGo1nmiP5IjCLFJhpg-L2XxX0mGMsC6kJcQ&key=AIzaSyADLqCeJAQo6qES8aNsfGH2n8fRjOAAMrQ",
      "https://maps.googleapis.com/maps/api/place/photo?maxwidth=400&photo_reference=AciIO2faNNU9utMYI4xoo5fmz3muuYFmghhSqsPC-rknISIl2lzyAKLALHeifBGKIsDejlFHtWOO6-yBM6P4oXTdWxPh71X-E8o9qOAjtm8vgoVX6R0T4lXHs6bCP7EuwpnsZB1kHOyi-KCZOlvo3bLTPXximAE4_fGCvywCL1kGNNOFha9WvivQZ3eHiMLVwLhDjBE5dcXf_bN1trARnYrbxBSQcjrjhYn_B2Tj268-VID7PbXhrWnF0Ad9Nc7H4ZM8iDYhPDBb_QNV4Kp0itBTcgWhyJcUbfLcxYi43_yGuJ3s-w&key=AIzaSyADLqCeJAQo6qES8aNsfGH2n8fRjOAAMrQ",
      "https://maps.googleapis.com/maps/api/place/photo?maxwidth=400&photo_reference=AciIO2ewgJ7Sg0QeZZNS9jSJBNMZcOFwtyq8g49GHGD-fFu9WTUhdtkARhJtKWkMmxvITSNrx73C4UtkrBfhLcB-SLqviw1UyRQqTwlPIQCM4CQ8jyOPbL5AIbPMSuE-vUQC27t4RTIwjGP4drWioGmNEhFJ9jKilgXrPqFnTTMmjAT3uvkiY7dQZQVy4GFpPOvijdLoq6sDozDV_aw-fxcxxJXfLiRIKe194sCOEdf0ZbwLvmV78H0nJu4MVwiAautdRLGLu6cSxDuDCG7PietN_838Hqu03mOeyvMJhHagU6pdBQ&key=AIzaSyADLqCeJAQo6qES8aNsfGH2n8fRjOAAMrQ",
      "https://maps.googleapis.com/maps/api/place/photo?maxwidth=400&photo_reference=AciIO2cfo6vOmbzHjqm_rqX-YEf6IGEK5vAxWClY-ubeGTDZ985iF9kOMHgf6AwxL3EfyYRrDmIJ6EjorJhA0sew4jtGWhba-NKORSi7clN7alGvK4mp2IYCGS_vXMpL22LSQ1px5pIbhLXBbbkEsOxO3Mrxj2i_5zhlWhUkv6c1ZTBNLddmlaBTk-pW3EbDo98fztqHggSizc7m3QjgJUwHu8C4lBYqDrEE8LgZT3pKwnADL92Uu_MSqzjTHXU5X9-JWZgg5UyLBSLENLbC64SsTh611EKRrvgUt58EhZgyFOaL_g&key=AIzaSyADLqCeJAQo6qES8aNsfGH2n8fRjOAAMrQ"
    ],
    "mobileExperience": {
      "score": 44,
      "loadTime": 0,
      "isResponsive": true,
      "touchFriendly": true,
      "textReadable": false,
      "navigationEasy": false,
      "issues": [
        "Mobile performance data unavailable - API configuration required"
      ],
      "recommendations": [
        "Configure Google PageSpeed Insights API for mobile analysis",
        "Enable mobile performance monitoring",
        "Test website on mobile devices manually"
      ]
    },
    "reviewsAnalysis": {
      "overallScore": 94,
      "totalReviews": 355,
      "averageRating": 4.7,
      "sentimentBreakdown": {
        "positive": 100,
        "neutral": 0,
        "negative": 0
      },
      "reviewSources": [
        "Google Business Profile (Limited)"
      ],
      "keyThemes": [
        "Service",
        "Food Quality"
      ],
      "recentReviews": [
        {
          "author": "David N",
          "rating": 5,
          "text": "Wow!  That’s the best pizza I’ve had in a very long time. Delicious. Excellent customer service.\nI’m impressed",
          "date": "2025-09-01T01:56:26.000Z",
          "platform": "Google Places"
        },
        {
          "author": "Chelsey Steinarsson",
          "rating": 5,
          "text": "Top Crust has fantastic pizza! They have gluten free and cauliflower crust options that actually taste really good!!! They have several specialty combinations and their wings are delicious! Every time we order the food is hot and fresh. You must try them!",
          "date": "2025-08-30T23:52:06.000Z",
          "platform": "Google Places"
        },
        {
          "author": "Alice Djubin",
          "rating": 5,
          "text": "Excellent pizza presentation with a generous amount of toppings evenly distributed across the pie. I placed a takeout order and it was ready a good 5 minutes before the estimated pickup time. Employees were pleasant and courteous. The pie was absolutely delicious!  This was my second time ordering and this store is now my go-to place for delicious pizza. I have already recommended Top Crust to my friends and neighbors. Thank you and keep up the great work!",
          "date": "2025-08-24T15:44:28.000Z",
          "platform": "Google Places"
        },
        {
          "author": "Christine Rowell",
          "rating": 5,
          "text": "Food was delicious! We got delivery so that’s the only reason the pizza was a little mis shaped! Tip would be tip wrap the rolls also with clear wrap to keep all the goodness in with them!",
          "date": "2025-07-23T22:15:52.000Z",
          "platform": "Google Places"
        },
        {
          "author": "Van E. Singelis (VMAN)",
          "rating": 5,
          "text": "Ordered the special large pizza with 10 hot wings!\nOh Mama.... Crispy golden crust, fresh ingredients, savory mushrooms with just the right amount of pepperoni.  Not to saucy, and the perfect complement of cheese.  Chicken wings extra crispy, bold, tangy, spicy and flavorful.\nJeff the owner and his kitchen staff always make you feel at home.  Give them a try, tell Jeff the VMAN sent you.  Oh did I mention the homemade cannoli's, HUGE!",
          "date": "2025-07-11T15:56:41.000Z",
          "platform": "Google Places"
        }
      ],
      "examples": {
        "positive": [
          {
            "author": "Van E. Singelis (VMAN)",
            "rating": 5,
            "text": "Ordered the special large pizza with 10 hot wings!\nOh Mama.... Crispy golden crust, fresh ingredients, savory mushrooms with just the right amount of pepperoni.  Not to saucy, and the perfect complement of cheese.  Chicken wings extra crispy, bold, tangy, spicy and flavorful.\nJeff the owner and his kitchen staff always make you feel at home.  Give them a try, tell Jeff the VMAN sent you.  Oh did I mention the homemade cannoli's, HUGE!",
            "date": "2025-07-11T15:56:41.000Z",
            "platform": "Google Places"
          },
          {
            "author": "Alice Djubin",
            "rating": 5,
            "text": "Excellent pizza presentation with a generous amount of toppings evenly distributed across the pie. I placed a takeout order and it was ready a good 5 minutes before the estimated pickup time. Employees were pleasant and courteous. The pie was absolutely delicious!  This was my second time ordering and this store is now my go-to place for delicious pizza. I have already recommended Top Crust to my friends and neighbors. Thank you and keep up the great work!",
            "date": "2025-08-24T15:44:28.000Z",
            "platform": "Google Places"
          },
          {
            "author": "David N",
            "rating": 5,
            "text": "Wow!  That’s the best pizza I’ve had in a very long time. Delicious. Excellent customer service.\nI’m impressed",
            "date": "2025-09-01T01:56:26.000Z",
            "platform": "Google Places"
          }
        ],
        "neutral": [],
        "negative": []
      },
      "customerMoodAnalysis": {
        "overallMood": "delighted",
        "sentimentSummary": "Customers are genuinely thrilled with their experience. With an average 5.0/5 rating across 5 recent reviews, your restaurant consistently exceeds expectations.",
        "sentimentDistribution": {
          "ecstatic": 20,
          "delighted": 80,
          "satisfied": 0,
          "neutral": 0,
          "frustrated": 0,
          "disappointed": 0,
          "angry": 0
        },
        "keyMoodIndicators": [
          {
            "theme": "food quality",
            "mentions": 8
          },
          {
            "theme": "slow service",
            "mentions": 1
          }
        ],
        "emotionalBreakdown": {
          "joy": 1,
          "satisfaction": 4,
          "disappointment": 0,
          "frustration": 0,
          "anger": 0
        },
        "businessInsights": {
          "strengthsPerceived": [
            "Customers love the crispy golden crust and fresh ingredients, making the pizza a standout choice. - social media marketing can showcase this strength",
            "The restaurant consistently delivers hot and fresh food, even offering gluten-free and cauliflower crust options that taste great. - SEO services can leverage this for better visibility",
            "The owner and staff provide excellent customer service, making customers feel at home and encouraging repeat visits. - Boostly marketing services can amplify this"
          ],
          "improvementOpportunities": [
            "Maintain current high standards",
            "Continue engaging with customer feedback",
            "Monitor reviews for improvement opportunities"
          ]
        },
        "detailedMetrics": {
          "totalReviews": 5,
          "averageRating": 5,
          "ratingDistribution": {
            "1": 0,
            "2": 0,
            "3": 0,
            "4": 0,
            "5": 100
          },
          "sentimentTrends": {
            "trend": "stable",
            "recentAverageRating": 5,
            "previousAverageRating": 5,
            "recentReviewsCount": 5
          }
        }
      },
      "trends": {
        "ratingTrend": "positive",
        "volumeTrend": "increasing",
        "responseRate": 75,
        "averageResponseTime": "2 days"
      },
      "recommendations": [
        {
          "category": "growth",
          "priority": "high",
          "title": "Generate More Reviews",
          "description": "Encourage satisfied customers to leave reviews",
          "impact": "Increase online credibility and visibility"
        }
      ],
      "googleReviews": {
        "reviews": [
          {
            "author": "David N",
            "rating": 5,
            "text": "Wow!  That’s the best pizza I’ve had in a very long time. Delicious. Excellent customer service.\nI’m impressed",
            "date": "2025-09-01T01:56:26.000Z",
            "platform": "Google Places"
          },
          {
            "author": "Chelsey Steinarsson",
            "rating": 5,
            "text": "Top Crust has fantastic pizza! They have gluten free and cauliflower crust options that actually taste really good!!! They have several specialty combinations and their wings are delicious! Every time we order the food is hot and fresh. You must try them!",
            "date": "2025-08-30T23:52:06.000Z",
            "platform": "Google Places"
          },
          {
            "author": "Alice Djubin",
            "rating": 5,
            "text": "Excellent pizza presentation with a generous amount of toppings evenly distributed across the pie. I placed a takeout order and it was ready a good 5 minutes before the estimated pickup time. Employees were pleasant and courteous. The pie was absolutely delicious!  This was my second time ordering and this store is now my go-to place for delicious pizza. I have already recommended Top Crust to my friends and neighbors. Thank you and keep up the great work!",
            "date": "2025-08-24T15:44:28.000Z",
            "platform": "Google Places"
          },
          {
            "author": "Christine Rowell",
            "rating": 5,
            "text": "Food was delicious! We got delivery so that’s the only reason the pizza was a little mis shaped! Tip would be tip wrap the rolls also with clear wrap to keep all the goodness in with them!",
            "date": "2025-07-23T22:15:52.000Z",
            "platform": "Google Places"
          },
          {
            "author": "Van E. Singelis (VMAN)",
            "rating": 5,
            "text": "Ordered the special large pizza with 10 hot wings!\nOh Mama.... Crispy golden crust, fresh ingredients, savory mushrooms with just the right amount of pepperoni.  Not to saucy, and the perfect complement of cheese.  Chicken wings extra crispy, bold, tangy, spicy and flavorful.\nJeff the owner and his kitchen staff always make you feel at home.  Give them a try, tell Jeff the VMAN sent you.  Oh did I mention the homemade cannoli's, HUGE!",
            "date": "2025-07-11T15:56:41.000Z",
            "platform": "Google Places"
          }
        ],
        "averageRating": 4.7,
        "totalReviews": 355
      }
    },
    "socialMediaLinks": {
      "facebook": "https://www.facebook.com/topcrustjupiterkitchen",
      "instagram": "https://www.instagram.com/topcrustjupiterkitchen",
      "twitter": null,
      "youtube": null,
      "tiktok": null,
      "linkedin": null
    },
    "profileAnalysis": null,
    "serpScreenshots": [],
    "restaurantSearchScreenshot": null,
    "calculatedScores": {
      "search": 58,
      "social": 100,
      "local": 73,
      "reviews": 88,
      "overall": 80
    },
    "originalScores": {
      "seo": 70,
      "overallScore": 69,
      "performance": 64,
      "userExperience": 60
    },
    "migratedAt": "2025-09-16T00:37:21.363Z"
  },
  "metadata": {
    "cachedAt": "2025-09-15T16:10:31.646Z",
    "expiresAt": "2025-10-15T16:10:31.646Z",
    "placeId": "ChIJHcvLWvTV3ogRuhXfThCi_G8",
    "restaurantName": "TopCrust Jupiter Kitchen",
    "cacheVersion": "2.0.0"
  }
}